[{
  "name": "PR1 FZZ - Precurso pedestre de Dornes",
  "description": "Percurso Pedestre e Ciclavél circular de 19 a 7 Km (segundo a variante) com vistas sobre Dornes e a Albufeira de Castelo de Bode. Maioritariamente em estradão florestal.",
  "directions": [39.771404,-8.269419],
  "url": "maps/pr1_fzz.jpg",
  "link": "https://mohawkhudson.org/our-preserves/bennett-hill-preserve/",
  "projection": ["EPSG:4326","+proj=longlat +datum=WGS84 +no_defs"],
  "extent": [-8.285752688273, 39.7404905569405, -8.228153378833, 39.7812214967215]
}]
